parzivalscalculator/__init__.py
parzivalscalculator-0.1.dist-info/LICENSE.txt
parzivalscalculator-0.1.dist-info/METADATA
parzivalscalculator-0.1.dist-info/WHEEL
parzivalscalculator-0.1.dist-info/top_level.txt
parzivalscalculator-0.1.dist-info/RECORD
