Metadata-Version: 2.1
Name: parzivalscalculator
Version: 0.1
Summary: This is just a simple calculator
Author: Kamran Akmal
Author-email: kamuakmal010@gmail.com
Classifier: Programming Language :: Python :: 3
Classifier: License :: OSI Approved :: MIT License
Classifier: Operating System :: OS Independent
License-File: LICENSE.txt
